snmpresponder/__init__.py
snmpresponder/cparser.py
snmpresponder/daemon.py
snmpresponder/endpoint.py
snmpresponder/error.py
snmpresponder/lazylog.py
snmpresponder/log.py
snmpresponder/macro.py
snmpresponder/next.py
snmpresponder/plugins/__init__.py
snmpresponder/plugins/manager.py
snmpresponder/plugins/status.py
snmpresponder/snmpresponderd.py
snmpresponder-0.0.6.dist-info/LICENSE.txt
snmpresponder-0.0.6.dist-info/METADATA
snmpresponder-0.0.6.dist-info/WHEEL
snmpresponder-0.0.6.dist-info/entry_points.txt
snmpresponder-0.0.6.dist-info/RECORD
